sharestats_item_editor/__init__.py
sharestats_item_editor/__main__.py
sharestats_item_editor/dialogs.py
sharestats_item_editor/mainwin.py
sharestats_item_editor/meta_info.py
sharestats_item_editor/taxonomy.json
sharestats_item_editor/taxonomy.py
sharestats_item_editor/rexam_item_editor/__init__.py
sharestats_item_editor/rexam_item_editor/__main__.py
sharestats_item_editor/rexam_item_editor/cli.py
sharestats_item_editor/rexam_item_editor/consts.py
sharestats_item_editor/rexam_item_editor/misc.py
sharestats_item_editor/rexam_item_editor/sysinfo.py
sharestats_item_editor/rexam_item_editor/gui/__init__.py
sharestats_item_editor/rexam_item_editor/gui/dialogs.py
sharestats_item_editor/rexam_item_editor/gui/essb.png
sharestats_item_editor/rexam_item_editor/gui/exam_compiler.py
sharestats_item_editor/rexam_item_editor/gui/gui_misc.py
sharestats_item_editor/rexam_item_editor/gui/json_settings.py
sharestats_item_editor/rexam_item_editor/gui/log.py
sharestats_item_editor/rexam_item_editor/gui/mainwin.py
sharestats_item_editor/rexam_item_editor/rexam/__init__.py
sharestats_item_editor/rexam_item_editor/rexam/exam.py
sharestats_item_editor/rexam_item_editor/rexam/extypes.py
sharestats_item_editor/rexam_item_editor/rexam/filepath.py
sharestats_item_editor/rexam_item_editor/rexam/git_info.py
sharestats_item_editor/rexam_item_editor/rexam/issue.py
sharestats_item_editor/rexam_item_editor/rexam/item.py
sharestats_item_editor/rexam_item_editor/rexam/item_database.py
sharestats_item_editor/rexam_item_editor/rexam/r_render.py
sharestats_item_editor/rexam_item_editor/rexam/rmd_file.py
sharestats_item_editor/rexam_item_editor/rexam/rmd_file_list.py
sharestats_item_editor/rexam_item_editor/templates/TemplateBlankCombination.Rmd
sharestats_item_editor/rexam_item_editor/templates/TemplateBlankNumber.Rmd
sharestats_item_editor/rexam_item_editor/templates/TemplateBlankTextEssay.Rmd
sharestats_item_editor/rexam_item_editor/templates/TemplateMultipleAnswer.Rmd
sharestats_item_editor-0.2.11.post2.dist-info/LICENSE
sharestats_item_editor-0.2.11.post2.dist-info/METADATA
sharestats_item_editor-0.2.11.post2.dist-info/WHEEL
sharestats_item_editor-0.2.11.post2.dist-info/entry_points.txt
sharestats_item_editor-0.2.11.post2.dist-info/top_level.txt
sharestats_item_editor-0.2.11.post2.dist-info/RECORD
